iceland/__init__.py
iceland/py.typed
iceland/version.py
iceland-0.1.7.dist-info/LICENSE
iceland-0.1.7.dist-info/METADATA
iceland-0.1.7.dist-info/WHEEL
iceland-0.1.7.dist-info/top_level.txt
iceland-0.1.7.dist-info/RECORD
